fastapi_cli_command/__init__.py
fastapi_cli_command/fastapi_cli.py
fastapi_cli_command/storage.py
fastapi_cli_command/bases/__init__.py
fastapi_cli_command/bases/cli.py
fastapi_cli_command/bases/command.py
fastapi_cli_command/cli/cli.py
fastapi_cli_command/cli/commands/generate_command.py
fastapi_cli_command/cli/generators/__init__.py
fastapi_cli_command/cli/generators/generator.py
fastapi_cli_command/cli/templates/__init__.py
fastapi_cli_command/cli/templates/base_template.py
fastapi_cli_command/cli/templates/command_template.py
fastapi_cli_command/cli/templates/controller_template.py
fastapi_cli_command/cli/templates/group_command_template.py
fastapi_cli_command/cli/templates/template_factory.py
fastapi_cli_command/decorators/__init__.py
fastapi_cli_command/decorators/cli_command.py
fastapi_cli_command/decorators/cli_command_group.py
fastapi_cli_command/decorators/command.py
fastapi_cli_command/enums/module_enum.py
fastapi_cli_command/helpers/__init__.py
fastapi_cli_command/helpers/load_module.py
fastapi_cli_command/helpers/parse_params.py
fastapi_cli_command/helpers/resolve_dependencies.py
fastapi_cli_command/helpers/snake_key.py
fastapi_cli_command-0.0.6.dist-info/METADATA
fastapi_cli_command-0.0.6.dist-info/WHEEL
fastapi_cli_command-0.0.6.dist-info/entry_points.txt
fastapi_cli_command-0.0.6.dist-info/licenses/LICENSE
fastapi_cli_command-0.0.6.dist-info/RECORD
