Metadata-Version: 2.3
Name: fastapi_cli_command
Version: 0.0.6
Summary: FastAPI CLI Command
Project-URL: Homepage, https://github.com/megatron-global/fastapi-cli-command
Project-URL: Bug Tracker, https://github.com/megatron-global/fastapi-cli-command/issues
Author-email: Harry Dang <quang.dang@megatron-solutions.com>
License-File: LICENSE
Classifier: License :: OSI Approved :: MIT License
Classifier: Operating System :: OS Independent
Classifier: Programming Language :: Python :: 3
Requires-Python: >=3.10
Requires-Dist: click>=8.1.7
Requires-Dist: fastapi>=0.109.1
